{
    "Bodies": [
        {
            "RefID": "Comp_5c7f63f9-c7f5-4307-a918-fa65c716c016_Body_panel",
            "Parent": "Comp_5c7f63f9-c7f5-4307-a918-fa65c716c016",
            "Name": "panel",
            "Phys": {
                "Mass": 0.10099966500883512,
                "Vol": 177.11245091499796,
                "COM": [
                    -0.0005174428715720205,
                    -0.3630708921074099,
                    1.5489229150568122
                ]
            }
        }
    ]
}